{
    "title": "Thông tư số 08/2024/TT-BNV của Bộ Nội vụ: Hướng dẫn thực hiện điều chỉnh mức trợ cấp hằng tháng đối với cán bộ, phường, thị trấn già yếu đã nghỉ việc",
    "so_ky_hieu": "08/2024/TT-BNV",
    "ngay_ban_hanh": "05-07-2024",
    "ngay_co_hieu_luc": "05-07-2024",
    "loai_van_ban": "Thông tư",
    "co_quan_ban_hanh": "Bộ Nội vụ",
    "nguoi_ky": "Phạm Thị Thanh Trà",
    "trich_yeu": "Hướng dẫn thực hiện điều chỉnh mức trợ cấp hằng tháng đối với cán bộ, phường, thị trấn già yếu đã nghỉ việc",
    "pdf_files": [
        [
            "08-bnv.pdf",
            "https://datafiles.chinhphu.vn/cpp/files/vbpq/2024/7/08-bnv.pdf"
        ]
    ]
}